{"deckDruid_":"[C] 咆哮德","deckHunter_":"[C] 打脸猎","deckMage_":"[C] 节奏法","deckPaladin_":"[C] 圣骑士","deckPriest_":"[S] 暗牧","deckRogue_":"[C] 节奏贼","deckShaman_":"[C] 节奏萨","deckWarlock_":"[C] 动物园","deckWarrior_":"[C] 战士","deckDemonHunter_":"[S] 魔猎","level_":60,"rankLevel_":35,"heroLevel_":"小德:60; 猎人:39; 法师:30; 圣骑:30;\r\n牧师:29; 盗贼:30; 萨满:30; 术士:30;\r\n战士:30; 魔猎:21","rankLevelShow_":"经典:35; 标准:50; 狂野:50","ckmc_":"炉石传说","width_":549,"height_":439,"x_":1378,"y_":608,"Description":"KanShuFan自用整合插件","AutoMode":11,"Level":60,"RankLevel":35,"Ckmc":"炉石传说","Width":549,"Height":439,"X":1378,"Y":608,"HeroLevel":"小德:60; 猎人:39; 法师:30; 圣骑:30;\r\n牧师:29; 盗贼:30; 萨满:30; 术士:30;\r\n战士:30; 魔猎:21","RankLevelShow":"经典:35; 标准:50; 狂野:50","Decks1":"[C] 咆哮德","Decks2":"[C] 打脸猎","Decks3":"[C] 节奏法","Decks4":"[C] 圣骑士","Decks5":"[S] 暗牧","Decks6":"[C] 节奏贼","Decks7":"[C] 节奏萨","Decks8":"[C] 动物园","Decks9":"[C] 战士","Decks10":"[S] 魔猎","Enabled":false,"Name":"KanShuFan"}